dictbox/__init__.py
dictbox-0.0.3.dist-info/LICENSE
dictbox-0.0.3.dist-info/METADATA
dictbox-0.0.3.dist-info/WHEEL
dictbox-0.0.3.dist-info/top_level.txt
dictbox-0.0.3.dist-info/RECORD
