Metadata-Version: 2.1
Name: dictbox
Version: 0.0.3
Summary: make it easy to use dict
Home-page: https://gitee.com/ZeroSeeker/dictbox
Author: ZeroSeeker
Author-email: zeroseeker@foxmail.com
License: UNKNOWN
Platform: UNKNOWN
Classifier: Programming Language :: Python :: 3
Classifier: License :: OSI Approved :: MIT License
Classifier: Operating System :: OS Independent
License-File: LICENSE
